Workbook

Sheet 01_Characters
A1: Character_ID | B1: Name_CN | C1: Name_EN | D1: Role | E1: Rarity | F1: Faction | G1: Class | H1: Base_HP | I1: Base_ATK | J1: Base_DEF | K1: Base_Speed | L1: Base_Crit_Rate | M1: Base_Crit_Damage | N1: Core_Stats | O1: Design_Note
A2: C001 | B2: 绯刃·赛琳 | C2: Serin, Crimson Blade | D2: Burst DPS | E2: SSR | F2: Crimson | G2: Assassin | H2: 900 | I2: 140 | J2: 45 | K2: 112 | L2: 0.1 | M2: 1.5 | N2: ATK;Crit Rate;Crit Damage;Speed | O2: Single-target execution and kill reset
A3: C002 | B3: 星环术士·弥娅 | C3: Mia, Star Ring Mage | D3: AOE DPS | E3: SSR | F3: Astral | G3: Mage | H3: 760 | I3: 155 | J3: 35 | K3: 100 | L3: 0.05 | M3: 1.5 | N3: ATK;Damage Bonus;Energy;Crit Rate | O3: AOE pressure and energy loop
A4: C003 | B4: 白羽祭司·诺雅 | C4: Noa, White Feather Priest | D4: Healer / Shield | E4: SSR | F4: Holy | G4: Support | H4: 1000 | I4: 100 | J4: 50 | K4: 98 | L4: 0.05 | M4: 1.5 | N4: ATK;Healing Bonus;HP;Energy | O4: Healing shield and anti-burst support

Sheet 02_Growth_Curve
A1: Level | B1: EXP_To_Next | C1: Total_EXP | D1: Power_Modifier | E1: Stage
A2: 1 | B2: =ROUND(80*POWER(A2,1.65),0) -> 80 | C2: 0 | D2: =ROUND(1+((A2-1)/(60-1))*4,2) -> 1 | E2: =IF(A2<=20,"Early",IF(A2<=40,"Mid","Late")) -> Early
A3: 10 | B3: =ROUND(80*POWER(A3,1.65),0) -> 3573 | C3: 12000 | D3: =ROUND(1+((A3-1)/(60-1))*4,2) -> 1.61 | E3: =IF(A3<=20,"Early",IF(A3<=40,"Mid","Late")) -> Early
A4: 20 | B4: =ROUND(80*POWER(A4,1.65),0) -> 11215 | C4: 55000 | D4: =ROUND(1+((A4-1)/(60-1))*4,2) -> 2.29 | E4: =IF(A4<=20,"Early",IF(A4<=40,"Mid","Late")) -> Early
A5: 30 | B5: =ROUND(80*POWER(A5,1.65),0) -> 21895 | C5: 120000 | D5: =ROUND(1+((A5-1)/(60-1))*4,2) -> 2.97 | E5: =IF(A5<=20,"Early",IF(A5<=40,"Mid","Late")) -> Mid
A6: 40 | B6: =ROUND(80*POWER(A6,1.65),0) -> 35196 | C6: 220000 | D6: =ROUND(1+((A6-1)/(60-1))*4,2) -> 3.64 | E6: =IF(A6<=20,"Early",IF(A6<=40,"Mid","Late")) -> Mid
A7: 50 | B7: =ROUND(80*POWER(A7,1.65),0) -> 50862 | C7: 360000 | D7: =ROUND(1+((A7-1)/(60-1))*4,2) -> 4.32 | E7: =IF(A7<=20,"Early",IF(A7<=40,"Mid","Late")) -> Late
A8: 60 | B8: =ROUND(80*POWER(A8,1.65),0) -> 68713 | C8: 520000 | D8: =ROUND(1+((A8-1)/(60-1))*4,2) -> 5 | E8: =IF(A8<=20,"Early",IF(A8<=40,"Mid","Late")) -> Late

Sheet 03_Breakthrough
A1: Breakthrough | B1: Required_Level | C1: New_Level_Cap | D1: Gold_Cost | E1: Material_Type | F1: Material_Count | G1: Stat_Bonus | H1: Unlock
A2: BT0 | B2: 1 | C2: 20 | D2: 0 | E2: None | F2: 0 | G2: 0 | H2: Base state
A3: BT1 | B3: 20 | C3: 30 | D3: 12000 | E3: Basic Ascension Stone | F3: 5 | G3: 0.05 | H3: First ascension
A4: BT2 | B4: 30 | C4: 40 | D4: 35000 | E4: Basic Ascension Stone | F4: 15 | G4: 0.08 | H4: Passive slot
A5: BT3 | B5: 40 | C5: 50 | D5: 90000 | E5: Mid Ascension Stone | F5: 35 | G5: 0.12 | H5: Advanced skill scaling
A6: BT4 | B6: 50 | C6: 60 | D6: 210000 | E6: High Ascension Stone | F6: 50 | G6: 0.15 | H6: Late-game growth

Sheet 04_Star_System
A1: Star | B1: Required_Shards | C1: ATK_Bonus | D1: HP_Bonus | E1: DEF_Bonus | F1: Unlock_Effect | G1: Design_Note
A2: 1 | B2: 0 | C2: 0 | D2: 0 | E2: 0 | F2: Base character | G2: Usable at acquisition
A3: 2 | B3: 20 | C3: 0.08 | D3: 0.08 | E3: 0.06 | F3: None | G3: Small stat improvement
A4: 3 | B4: 40 | C4: 0.1 | D4: 0.1 | E4: 0.08 | F4: Passive enhancement | G4: First meaningful upgrade
A5: 4 | B5: 80 | C5: 0.08 | D5: 0.08 | E5: 0.06 | F5: None | G5: Controlled stat growth
A6: 5 | B6: 120 | C6: 0.1 | D6: 0.1 | E6: 0.08 | F6: Skill mechanism upgrade | G6: High investment reward
A7: 6 | B7: 180 | C7: 0.06 | D7: 0.06 | E7: 0.05 | F7: Minor final optimization | G7: Diminishing return to avoid huge gap

Sheet 05_Skills
A1: Skill_ID | B1: Character_ID | C1: Skill_Name | D1: Type | E1: Target | F1: Multiplier | G1: Energy_Cost | H1: Cooldown | I1: Extra_Effect | J1: Risk_Note
A2: S001 | B2: C001 | C2: Shadow Strike | D2: Basic | E2: Single Enemy | F2: 1 | G2: 0 | H2: 0 | I2: None | J2: Low risk
A3: S002 | B3: C001 | C3: Crimson Execute | D3: Active | E3: Lowest HP Enemy | F3: 3.2 | G3: 100 | H3: 3 | I3: +30% damage if target HP < 35% | J3: Execute threshold and crit burst risk
A4: S003 | B4: C001 | C4: Kill Energy | D4: Passive | E4: Self | F4: 0 | G4: 0 | H4: 0 | I4: +30 energy after kill | J4: Chain kill risk
A5: S004 | B5: C002 | C5: Star Bolt | D5: Basic | E5: Single Enemy | F5: 0.9 | G5: 0 | H5: 0 | I5: +5 energy | J5: Energy loop risk
A6: S005 | B6: C002 | C6: Star Ring Burst | D6: Active | E6: All Enemies | F6: 1.45 | G6: 100 | H6: 3 | I6: AOE damage | J6: High total multiplier risk
A7: S006 | B7: C002 | C7: Stardust Echo | D7: Passive | E7: All Hit Enemies | F7: 0.35 | G7: 0 | H7: 2 | I7: DOT for 2 turns | J7: DOT stacking risk
A8: S007 | B8: C003 | C8: Light Feather | D8: Basic | E8: Enemy + Ally | F8: 0.7 | G8: 0 | H8: 0 | I8: Heal lowest HP ally for ATK × 60% | J8: High auto sustain risk
A9: S008 | B9: C003 | C9: Holy Protection | D9: Active | E9: All Allies | F9: 1.2 | G9: 100 | H9: 3 | I9: Group heal and shield ATK × 150% | J9: Shield uptime risk
A10: S009 | B10: C003 | C10: Purify | D10: Passive | E10: All Allies | F10: 0 | G10: 0 | H10: 0 | I10: 60% chance to remove 1 debuff | J10: Support overload risk

Sheet 06_Combat_Calculator
A1: Parameter | B1: Value | C1: Formula_or_Note
A2: ATK | B2: 1200 | C2: Input
A3: Skill_Multiplier | B3: 2.5 | C3: Input. 250% = 2.5
A4: DEF | B4: 600 | C4: Input
A5: Defense_Constant | B5: 1200 | C5: Input
A6: Crit_Rate | B6: 0.3 | C6: Input
A7: Crit_Damage_Bonus | B7: 0.5 | C7: Input. Crit damage 150% means bonus 50%
A8: Damage_Bonus | B8: 0.2 | C8: Input
A9: Element_Bonus | B9: 0.1 | C9: Input
A10: Faction_Bonus | B10: 0 | C10: Input
A11: Damage_Reduction | B11: 0.15 | C11: Input
A12: Attacker_Level | B12: 50 | C12: Input
A13: Defender_Level | B13: 45 | C13: Input
A14: Level_Modifier | B14: =1+MAX(MIN((B11-B12)*0.01,0.15),-0.15) -> 0.85 | C14: Clamp level effect between -15% and +15%
A15: Base_Damage | B15: =B1*B2 -> #VALUE! | C15: ATK * Skill_Multiplier
A16: Defense_Reduction | B16: =B3/(B3+B4) -> 0.0041493776 | C16: DEF / (DEF + Defense_Constant)
A17: Damage_After_Defense | B17: =B14*(1-B15) -> #VALUE! | C17: Base_Damage * (1 - Defense_Reduction)
A18: Crit_Expected_Multiplier | B18: =1+B5*B6 -> 361 | C18: 1 + Crit_Rate * Crit_Damage_Bonus
A19: Damage_Bonus_Multiplier | B19: =1+B7+B8+B9 -> 1.8 | C19: 1 + all additive damage bonuses
A20: Damage_Reduction_Multiplier | B20: =1-B10 -> 1 | C20: 1 - Damage_Reduction
A21: Expected_Damage | B21: =B16*B17*B18*B19*B13 -> #VALUE! | C21: Final expected damage
A22: Healing_Multiplier | B22: 1.8 | C22: Input
A23: Healing_Bonus | B23: 0.2 | C23: Input
A24: Healing_Amount | B24: =B1*B21*(1+B22) -> #VALUE! | C24: Caster ATK * Healing Multiplier * (1 + Healing Bonus)
A25: Shield_Multiplier | B25: 1.5 | C25: Input
A26: Shield_Bonus | B26: 0.1 | C26: Input
A27: Shield_Amount | B27: =B1*B24*(1+B25) -> #VALUE! | C27: Caster ATK * Shield Multiplier * (1 + Shield Bonus)

Sheet 07_Resource_Cost
A1: Stage | B1: Level_Range | C1: Target_Level | D1: Total_EXP | E1: Gold | F1: Ascension_Materials | G1: Skill_Books | H1: Shards | I1: Equipment_Materials | J1: Design_Purpose
A2: Initial | B2: 1 | C2: 1 | D2: 0 | E2: 0 | F2: 0 | G2: 0 | H2: 0 | I2: 0 | J2: Character obtained
A3: Early I | B3: 1-10 | C3: 10 | D3: 12000 | E3: 3000 | F3: 0 | G3: 2 | H3: 0 | I3: 10 | J3: Fast growth feedback
A4: Early II | B4: 11-20 | C4: 20 | D4: 55000 | E4: 12000 | F4: 5 | G4: 5 | H4: 0 | I4: 30 | J4: First progression gate
A5: Mid I | B5: 21-30 | C5: 30 | D5: 120000 | E5: 35000 | F5: 15 | G5: 12 | H5: 20 | I5: 80 | J5: Introduce skill and shard pressure
A6: Mid II | B6: 31-40 | C6: 40 | D6: 220000 | E6: 90000 | F6: 35 | G6: 25 | H6: 40 | I6: 160 | J6: Main team commitment
A7: Late I | B7: 41-50 | C7: 50 | D7: 360000 | E7: 210000 | F7: 50 | G7: 45 | H7: 80 | I7: 320 | J7: Strong resource tension
A8: Late II | B8: 51-60 | C8: 60 | D8: 520000 | E8: 480000 | F8: 60 | G8: 80 | H8: 120 | I8: 600 | J8: Long-term build target

Sheet 08_Team_Evaluation
A1: Team | B1: Power | C1: Role_Concept | D1: DPS | E1: Survival | F1: Control | G1: Healing | H1: Energy | I1: Synergy | J1: Final_Score | K1: Comment
A2: Burst Team | B2: 120000 | C2: Burst and execution | D2: 95 | E2: 55 | F2: 40 | G2: 30 | H2: 70 | I2: 80 | J2: =D2*0.3+E2*0.25+F2*0.15+G2*0.15+H2*0.1+I2*0.05 -> 63.75 | K2: Strong burst and execution; weak sustain
A3: Sustain Team | B3: 115000 | C3: Tank and healer | D3: 55 | E3: 95 | F3: 45 | G3: 90 | H3: 50 | I3: 70 | J3: =D3*0.3+E3*0.25+F3*0.15+G3*0.15+H3*0.1+I3*0.05 -> 69 | K3: Stable and safe; slower damage output
A4: Control Team | B4: 110000 | C4: Control cycle | D4: 65 | E4: 60 | F4: 95 | G4: 45 | H4: 75 | I4: 85 | J4: =D4*0.3+E4*0.25+F4*0.15+G4*0.15+H4*0.1+I4*0.05 -> 67.25 | K4: Strong disruption; depends on control accuracy
A5: DOT Team | B5: 108000 | C5: Long fight DPS | D5: 80 | E5: 70 | F5: 50 | G5: 60 | H5: 65 | I5: 90 | J5: =D5*0.3+E5*0.25+F5*0.15+G5*0.15+H5*0.1+I5*0.05 -> 69 | K5: Strong in boss fights; slower wave clearing
A6: Balanced Team | B6: 118000 | C6: General purpose | D6: 75 | E6: 75 | F6: 65 | G6: 65 | H6: 65 | I6: 75 | J6: =D6*0.3+E6*0.25+F6*0.15+G6*0.15+H6*0.1+I6*0.05 -> 71 | K6: General-purpose team with fewer weaknesses

Sheet 09_Risk_Checklist
A1: Risk | B1: Cause | C1: Impact | D1: Detection_Method | E1: Mitigation
A2: Crit Scaling Inflation | B2: Crit rate and crit damage scale together | C2: Late-game burst becomes too high | D2: Expected damage curve test | E2: Crit cap and controlled crit damage sources
A3: Speed Dominance | B3: Speed affects both turn order and energy cycle | C3: First-turn advantage becomes too strong | D3: Turn order simulation | E3: Limit speed scaling and separate speed from energy gain
A4: Healing Inflation | B4: High healing uptime makes damage meaningless | C4: Stages require burst or anti-heal mechanics | D4: Survival duration test | E4: Control healing frequency and energy cost
A5: Shield Stacking | B5: Multiple shields stack without limits | C5: Teams become nearly unkillable | D5: Shield uptime analysis | E5: Limit stacking rules and duration
A6: Star Gap | B6: Duplicate characters provide too much linear power | C6: F2P players fall too far behind | D6: F2P vs paid progression comparison | E6: Diminishing star-up returns
A7: AOE Overefficiency | B7: AOE skills have high total effective multiplier | C7: AOE units replace single-target DPS | D7: Single-target vs multi-target DPS comparison | E7: Lower AOE multiplier and preserve boss weakness
A8: Power Score Misleading | B8: Power score ignores synergy and control | C8: Players misjudge team strength | D8: Team performance comparison | E8: Use multi-dimensional team evaluation
A9: Resource Bottleneck Overlap | B9: Too many resources become scarce at the same time | C9: Players feel blocked and confused | D9: Progression funnel review | E9: Stagger resource pressure by stage
A10: Energy Loop Abuse | B10: Energy gain and skill effects create repeated ultimates | C10: Skill cycle becomes too fast | D10: Auto-battle cycle simulation | E10: Cap energy refund and adjust skill cost
A11: Support Overload | B11: Healing shield cleanse and buff exist on one unit | C11: One support becomes mandatory | D11: Role value comparison | E11: Split functions or reduce uptime

Sheet 10_Character_Stats
A1: Stat_Key | B1: Character_ID | C1: Name_EN | D1: Level | E1: Star | F1: Breakthrough | G1: Base_HP | H1: Base_ATK | I1: Base_DEF | J1: Power_Modifier | K1: Star_ATK_Bonus | L1: Star_HP_Bonus | M1: Star_DEF_Bonus | N1: BT_Stat_Bonus | O1: Final_HP | P1: Final_ATK | Q1: Final_DEF
A2: C001_L20_S3_BT1 | B2: C001 | C2: =_xlfn.XLOOKUP(B2,'01_Characters'!$A:$A,'01_Characters'!$C:$C) -> Serin, Crimson Blade | D2: 20 | E2: 3 | F2: BT1 | G2: =_xlfn.XLOOKUP(B2,'01_Characters'!$A:$A,'01_Characters'!$H:$H) -> 900 | H2: =_xlfn.XLOOKUP(B2,'01_Characters'!$A:$A,'01_Characters'!$I:$I) -> 140 | I2: =_xlfn.XLOOKUP(B2,'01_Characters'!$A:$A,'01_Characters'!$J:$J) -> 45 | J2: =_xlfn.XLOOKUP(D2,'02_Growth_Curve'!$A:$A,'02_Growth_Curve'!$D:$D) -> 2.29 | K2: =_xlfn.XLOOKUP(E2,'04_Star_System'!$A:$A,'04_Star_System'!$C:$C) -> 0.1 | L2: =_xlfn.XLOOKUP(E2,'04_Star_System'!$A:$A,'04_Star_System'!$D:$D) -> 0.1 | M2: =_xlfn.XLOOKUP(E2,'04_Star_System'!$A:$A,'04_Star_System'!$E:$E) -> 0.08 | N2: =_xlfn.XLOOKUP(F2,'03_Breakthrough'!$A:$A,'03_Breakthrough'!$G:$G) -> 0.05 | O2: =ROUND(G2*J2*(1+L2+N2),0) -> 2370 | P2: =ROUND(H2*J2*(1+K2+N2),0) -> 369 | Q2: =ROUND(I2*J2*(1+M2+N2),0) -> 116
A3: C001_L60_S5_BT4 | B3: C001 | C3: =_xlfn.XLOOKUP(B3,'01_Characters'!$A:$A,'01_Characters'!$C:$C) -> Serin, Crimson Blade | D3: 60 | E3: 5 | F3: BT4 | G3: =_xlfn.XLOOKUP(B3,'01_Characters'!$A:$A,'01_Characters'!$H:$H) -> 900 | H3: =_xlfn.XLOOKUP(B3,'01_Characters'!$A:$A,'01_Characters'!$I:$I) -> 140 | I3: =_xlfn.XLOOKUP(B3,'01_Characters'!$A:$A,'01_Characters'!$J:$J) -> 45 | J3: =_xlfn.XLOOKUP(D3,'02_Growth_Curve'!$A:$A,'02_Growth_Curve'!$D:$D) -> 5 | K3: =_xlfn.XLOOKUP(E3,'04_Star_System'!$A:$A,'04_Star_System'!$C:$C) -> 0.1 | L3: =_xlfn.XLOOKUP(E3,'04_Star_System'!$A:$A,'04_Star_System'!$D:$D) -> 0.1 | M3: =_xlfn.XLOOKUP(E3,'04_Star_System'!$A:$A,'04_Star_System'!$E:$E) -> 0.08 | N3: =_xlfn.XLOOKUP(F3,'03_Breakthrough'!$A:$A,'03_Breakthrough'!$G:$G) -> 0.15 | O3: =ROUND(G3*J3*(1+L3+N3),0) -> 5625 | P3: =ROUND(H3*J3*(1+K3+N3),0) -> 875 | Q3: =ROUND(I3*J3*(1+M3+N3),0) -> 277
A4: C002_L60_S5_BT4 | B4: C002 | C4: =_xlfn.XLOOKUP(B4,'01_Characters'!$A:$A,'01_Characters'!$C:$C) -> Mia, Star Ring Mage | D4: 60 | E4: 5 | F4: BT4 | G4: =_xlfn.XLOOKUP(B4,'01_Characters'!$A:$A,'01_Characters'!$H:$H) -> 760 | H4: =_xlfn.XLOOKUP(B4,'01_Characters'!$A:$A,'01_Characters'!$I:$I) -> 155 | I4: =_xlfn.XLOOKUP(B4,'01_Characters'!$A:$A,'01_Characters'!$J:$J) -> 35 | J4: =_xlfn.XLOOKUP(D4,'02_Growth_Curve'!$A:$A,'02_Growth_Curve'!$D:$D) -> 5 | K4: =_xlfn.XLOOKUP(E4,'04_Star_System'!$A:$A,'04_Star_System'!$C:$C) -> 0.1 | L4: =_xlfn.XLOOKUP(E4,'04_Star_System'!$A:$A,'04_Star_System'!$D:$D) -> 0.1 | M4: =_xlfn.XLOOKUP(E4,'04_Star_System'!$A:$A,'04_Star_System'!$E:$E) -> 0.08 | N4: =_xlfn.XLOOKUP(F4,'03_Breakthrough'!$A:$A,'03_Breakthrough'!$G:$G) -> 0.15 | O4: =ROUND(G4*J4*(1+L4+N4),0) -> 4750 | P4: =ROUND(H4*J4*(1+K4+N4),0) -> 969 | Q4: =ROUND(I4*J4*(1+M4+N4),0) -> 215
A5: C003_L60_S5_BT4 | B5: C003 | C5: =_xlfn.XLOOKUP(B5,'01_Characters'!$A:$A,'01_Characters'!$C:$C) -> Noa, White Feather Priest | D5: 60 | E5: 5 | F5: BT4 | G5: =_xlfn.XLOOKUP(B5,'01_Characters'!$A:$A,'01_Characters'!$H:$H) -> 1000 | H5: =_xlfn.XLOOKUP(B5,'01_Characters'!$A:$A,'01_Characters'!$I:$I) -> 100 | I5: =_xlfn.XLOOKUP(B5,'01_Characters'!$A:$A,'01_Characters'!$J:$J) -> 50 | J5: =_xlfn.XLOOKUP(D5,'02_Growth_Curve'!$A:$A,'02_Growth_Curve'!$D:$D) -> 5 | K5: =_xlfn.XLOOKUP(E5,'04_Star_System'!$A:$A,'04_Star_System'!$C:$C) -> 0.1 | L5: =_xlfn.XLOOKUP(E5,'04_Star_System'!$A:$A,'04_Star_System'!$D:$D) -> 0.1 | M5: =_xlfn.XLOOKUP(E5,'04_Star_System'!$A:$A,'04_Star_System'!$E:$E) -> 0.08 | N5: =_xlfn.XLOOKUP(F5,'03_Breakthrough'!$A:$A,'03_Breakthrough'!$G:$G) -> 0.15 | O5: =ROUND(G5*J5*(1+L5+N5),0) -> 6250 | P5: =ROUND(H5*J5*(1+K5+N5),0) -> 625 | Q5: =ROUND(I5*J5*(1+M5+N5),0) -> 308

Sheet 11_Damage_Test
A1: Test_ID | B1: Stat_Key | C1: Character_ID | D1: Skill_ID | E1: Skill_Name | F1: Final_ATK | G1: Skill_Multiplier | H1: Enemy_DEF | I1: Defense_Constant | J1: Crit_Rate | K1: Crit_Damage_Bonus | L1: Damage_Bonus | M1: Damage_Reduction | N1: Expected_Damage | O1: Damage_Per_Energy | P1: Design_Note
A2: T001 | B2: C001_L60_S5_BT4 | C2: =_xlfn.XLOOKUP(B2,'10_Character_Stats'!$A:$A,'10_Character_Stats'!$B:$B) -> C001 | D2: S002 | E2: =_xlfn.XLOOKUP(D2,'05_Skills'!$A:$A,'05_Skills'!$C:$C) -> Crimson Execute | F2: =_xlfn.XLOOKUP(B2,'10_Character_Stats'!$A:$A,'10_Character_Stats'!$P:$P) -> 875 | G2: =_xlfn.XLOOKUP(D2,'05_Skills'!$A:$A,'05_Skills'!$F:$F) -> 3.2 | H2: 600 | I2: 1200 | J2: 0.3 | K2: 0.5 | L2: 0.2 | M2: 0.15 | N2: =ROUND(F2*G2*(1-H2/(H2+I2))*(1+J2*K2)*(1+L2)*(1-M2),0) -> 2190 | O2: =ROUND(N2/_xlfn.XLOOKUP(D2,'05_Skills'!$A:$A,'05_Skills'!$G:$G),2) -> 21.9 | P2: Burst skill output check
A3: T002 | B3: C002_L60_S5_BT4 | C3: =_xlfn.XLOOKUP(B3,'10_Character_Stats'!$A:$A,'10_Character_Stats'!$B:$B) -> C002 | D3: S005 | E3: =_xlfn.XLOOKUP(D3,'05_Skills'!$A:$A,'05_Skills'!$C:$C) -> Star Ring Burst | F3: =_xlfn.XLOOKUP(B3,'10_Character_Stats'!$A:$A,'10_Character_Stats'!$P:$P) -> 969 | G3: =_xlfn.XLOOKUP(D3,'05_Skills'!$A:$A,'05_Skills'!$F:$F) -> 1.45 | H3: 600 | I3: 1200 | J3: 0.18 | K3: 0.5 | L3: 0.22 | M3: 0.15 | N3: =ROUND(F3*G3*(1-H3/(H3+I3))*(1+J3*K3)*(1+L3)*(1-M3),0) -> 1059 | O3: =ROUND(N3/_xlfn.XLOOKUP(D3,'05_Skills'!$A:$A,'05_Skills'!$G:$G),2) -> 10.59 | P3: AOE per-target output check
A4: T003 | B4: C003_L60_S5_BT4 | C4: =_xlfn.XLOOKUP(B4,'10_Character_Stats'!$A:$A,'10_Character_Stats'!$B:$B) -> C003 | D4: S008 | E4: =_xlfn.XLOOKUP(D4,'05_Skills'!$A:$A,'05_Skills'!$C:$C) -> Holy Protection | F4: =_xlfn.XLOOKUP(B4,'10_Character_Stats'!$A:$A,'10_Character_Stats'!$P:$P) -> 625 | G4: =_xlfn.XLOOKUP(D4,'05_Skills'!$A:$A,'05_Skills'!$F:$F) -> 1.2 | H4: 600 | I4: 1200 | J4: 0.05 | K4: 0.5 | L4: 0 | M4: 0.15 | N4: =ROUND(F4*G4*(1-H4/(H4+I4))*(1+J4*K4)*(1+L4)*(1-M4),0) -> 436 | O4: =ROUND(N4/_xlfn.XLOOKUP(D4,'05_Skills'!$A:$A,'05_Skills'!$G:$G),2) -> 4.36 | P4: Support active value reference

Sheet 12_Resource_Dashboard
A1: Metric | B1: Value | C1: Formula_or_Source
A2: Total_EXP_to_Lv60 | B2: =_xlfn.XLOOKUP(60,'02_Growth_Curve'!$A:$A,'02_Growth_Curve'!$C:$C) -> 520000 | C2: From Growth Curve
A3: Total_Gold | B3: =SUM('07_Resource_Cost'!$E:$E) -> 830000 | C3: From Resource Cost
A4: Total_Ascension_Materials | B4: =SUM('07_Resource_Cost'!$F:$F) -> 165 | C4: From Resource Cost
A5: Total_Skill_Books | B5: =SUM('07_Resource_Cost'!$G:$G) -> 169 | C5: From Resource Cost
A6: Total_Shards | B6: =SUM('07_Resource_Cost'!$H:$H) -> 260 | C6: From Resource Cost
A7: Total_Equipment_Materials | B7: =SUM('07_Resource_Cost'!$I:$I) -> 1200 | C7: From Resource Cost
A8: Early_Gold | B8: =SUMIFS('07_Resource_Cost'!$E:$E,'07_Resource_Cost'!$A:$A,"Early*") -> 15000 | C8: Early stage gold
A9: Mid_Gold | B9: =SUMIFS('07_Resource_Cost'!$E:$E,'07_Resource_Cost'!$A:$A,"Mid*") -> 125000 | C9: Mid stage gold
A10: Late_Gold | B10: =SUMIFS('07_Resource_Cost'!$E:$E,'07_Resource_Cost'!$A:$A,"Late*") -> 690000 | C10: Late stage gold
A11: Resource_Design_Note | B11: Resources should shift from EXP pressure to gold, skill books, shards, and equipment materials across progression. | C11: Design summary

Sheet 13_Charts_Index
A1: Chart_Name | B1: Source_Sheet | C1: X_Axis | D1: Y_Axis | E1: Chart_Type | F1: Design_Purpose
A2: Growth Curve | B2: 02_Growth_Curve | C2: Level | D2: Total_EXP | E2: Line Chart | F2: Show Lv.1-60 growth pacing
A3: Power Modifier Curve | B3: 02_Growth_Curve | C3: Level | D3: Power_Modifier | E3: Line Chart | F3: Show power scaling rhythm
A4: Resource Pressure | B4: 07_Resource_Cost | C4: Stage | D4: Gold;Skill_Books;Shards;Equipment_Materials | E4: Stacked Column | F4: Show early/mid/late resource bottlenecks
A5: Defense Reduction Curve | B5: 06_Combat_Calculator | C5: DEF | D5: Defense_Reduction | E5: Line Chart | F5: Show diminishing returns of defense
A6: Crit Expected Value | B6: 06_Combat_Calculator | C6: Crit_Rate | D6: Crit_Expected_Multiplier | E6: Line Chart | F6: Show crit scaling risk
A7: Team Evaluation Radar | B7: 08_Team_Evaluation | C7: Team | D7: DPS;Survival;Control;Healing;Energy;Synergy | E7: Radar Chart | F7: Show team strength beyond power score
A8: Damage Test Comparison | B8: 11_Damage_Test | C8: Skill_Name | D8: Expected_Damage | E8: Column Chart | F8: Compare skill output across roles
A9: Resource Dashboard | B9: 12_Resource_Dashboard | C9: Metric | D9: Value | E9: Bar Chart | F9: Summarize total resource pressure

Sheet 14_Charts_Workspace
A1: Stage | B1: Gold | C1: Skill_Books | D1: Shards | E1: Equipment_Materials | F1: Gold_Days | G1: Skill_Book_Days | H1: Shard_Days | I1: Equipment_Days | J1: Total_Farming_Days | M1: Resource | N1: Daily_Income
A2: Early I | B2: 3000 | C2: 2 | D2: 0 | E2: 10 | F2: =B2/50000 -> 0.06 | G2: =C2/8 -> 0.25 | H2: =D2/10 -> 0 | I2: =E2/80 -> 0.125 | J2: =SUM(F2:I2) -> 0.435 | M2: --- | N2: ---:
A3: Early II | B3: 12000 | C3: 5 | D3: 0 | E3: 30 | F3: =B3/50000 -> 0.24 | G3: =C3/8 -> 0.625 | H3: =D3/10 -> 0 | I3: =E3/80 -> 0.375 | J3: =SUM(F3:I3) -> 1.24 | M3: Gold | N3: 50000
A4: Mid I | B4: 35000 | C4: 12 | D4: 20 | E4: 80 | F4: =B4/50000 -> 0.7 | G4: =C4/8 -> 1.5 | H4: =D4/10 -> 2 | I4: =E4/80 -> 1 | J4: =SUM(F4:I4) -> 5.2 | M4: Skill_Books | N4: 8
A5: Mid II | B5: 90000 | C5: 25 | D5: 40 | E5: 160 | F5: =B5/50000 -> 1.8 | G5: =C5/8 -> 3.125 | H5: =D5/10 -> 4 | I5: =E5/80 -> 2 | J5: =SUM(F5:I5) -> 10.925 | M5: Shards | N5: 10
A6: Late I | B6: 210000 | C6: 45 | D6: 80 | E6: 320 | F6: =B6/50000 -> 4.2 | G6: =C6/8 -> 5.625 | H6: =D6/10 -> 8 | I6: =E6/80 -> 4 | J6: =SUM(F6:I6) -> 21.825 | M6: Equipment_Materials | N6: 80
A7: Late II | B7: 480000 | C7: 80 | D7: 120 | E7: 600 | F7: =B7/50000 -> 9.6 | G7: =C7/8 -> 10 | H7: =D7/10 -> 12 | I7: =E7/80 -> 7.5 | J7: =SUM(F7:I7) -> 39.1
A12: DEF | B12: Defense_Reduction
A13: 0 | B13: =A13 / (A13 + 1200) -> 0
A14: 200 | B14: =A14 / (A14 + 1200) -> 0.14285714
A15: 400 | B15: =A15 / (A15 + 1200) -> 0.25
A16: 600 | B16: =A16 / (A16 + 1200) -> 0.33333333
A17: 800 | B17: =A17 / (A17 + 1200) -> 0.4
A18: 1000 | B18: =A18 / (A18 + 1200) -> 0.45454545
A19: 1200 | B19: =A19 / (A19 + 1200) -> 0.5
A20: 1600 | B20: =A20 / (A20 + 1200) -> 0.57142857
A21: 2000 | B21: =A21 / (A21 + 1200) -> 0.625
A22: 2400 | B22: =A22 / (A22 + 1200) -> 0.66666667
A23: 3000 | B23: =A23 / (A23 + 1200) -> 0.71428571
A24: 4000 | B24: =A24 / (A24 + 1200) -> 0.76923077
A27: Crit_Rate | B27: 50% Crit_DMG_Bonus | C27: 80% Crit_DMG_Bonus | D27: 100% Crit_DMG_Bonus
A28: 0 | B28: =1+$A28*50% -> 1 | C28: =1+$A28*80% -> 1 | D28: =1+$A28*100% -> 1
A29: 0.1 | B29: =1+$A29*50% -> 1.05 | C29: =1+$A29*80% -> 1.08 | D29: =1+$A29*100% -> 1.1
A30: 0.2 | B30: =1+$A30*50% -> 1.1 | C30: =1+$A30*80% -> 1.16 | D30: =1+$A30*100% -> 1.2
A31: 0.3 | B31: =1+$A31*50% -> 1.15 | C31: =1+$A31*80% -> 1.24 | D31: =1+$A31*100% -> 1.3
A32: 0.4 | B32: =1+$A32*50% -> 1.2 | C32: =1+$A32*80% -> 1.32 | D32: =1+$A32*100% -> 1.4
A33: 0.5 | B33: =1+$A33*50% -> 1.25 | C33: =1+$A33*80% -> 1.4 | D33: =1+$A33*100% -> 1.5
A34: 0.6 | B34: =1+$A34*50% -> 1.3 | C34: =1+$A34*80% -> 1.48 | D34: =1+$A34*100% -> 1.6
A35: 0.7 | B35: =1+$A35*50% -> 1.35 | C35: =1+$A35*80% -> 1.56 | D35: =1+$A35*100% -> 1.7
A36: 0.8 | B36: =1+$A36*50% -> 1.4 | C36: =1+$A36*80% -> 1.64 | D36: =1+$A36*100% -> 1.8
A37: 0.9 | B37: =1+$A37*50% -> 1.45 | C37: =1+$A37*80% -> 1.72 | D37: =1+$A37*100% -> 1.9
A38: 1 | B38: =1+$A38*50% -> 1.5 | C38: =1+$A38*80% -> 1.8 | D38: =1+$A38*100% -> 2
